Workbook

Sheet BSE_500_LIVE
A1: BSE Code | B1: Company Name | C1: BSE_CMP_Official | D1: BSE_52W_High_Official | E1: BSE_52W_Low_Official | F1: Last Refreshed | G1: Source URL
A2: 500008 | B2: Amara Raja Energy & Mobility Ltd | G2: https://www.bseindia.com/stock-share-price/Amara-Raja-Energy-&-Mobility-Ltd/500008/
A3: 500034 | B3: Bajaj Finance Ltd | G3: https://www.bseindia.com/stock-share-price/Bajaj-Finance-Ltd/500034/
A4: 500055 | B4: Bombay Dyeing | G4: https://www.bseindia.com/stock-share-price/Bombay-Dyeing/500055/
A5: 500059 | B5: Birla Power Solutions Ltd | G5: https://www.bseindia.com/stock-share-price/Birla-Power-Solutions-Ltd/500059/
A6: 500089 | B6: Dichloromethane | G6: https://www.bseindia.com/stock-share-price/Dichloromethane/500089/
A7: 500112 | B7: State Bank Of India | G7: https://www.bseindia.com/stock-share-price/State-Bank-Of-India/500112/
A8: 500128 | B8: Electrosteel Castings Ltd | G8: https://www.bseindia.com/stock-share-price/Electrosteel-Castings-Ltd/500128/
A9: 500143 | B9: GTL Ltd | G9: https://www.bseindia.com/stock-share-price/GTL-Ltd/500143/
A10: 500147 | B10: Usha Martin Ltd | G10: https://www.bseindia.com/stock-share-price/Usha-Martin-Ltd/500147/
A11: 500170 | B11: National Chemicals | G11: https://www.bseindia.com/stock-share-price/National-Chemicals/500170/
A12: 500182 | B12: Hero MotoCorp Ltd | G12: https://www.bseindia.com/stock-share-price/Hero-MotoCorp-Ltd/500182/
A13: 500184 | B13: Himadri Speciality Chemical Ltd | G13: https://www.bseindia.com/stock-share-price/Himadri-Speciality-Chemical-Ltd/500184/
... A222: 518017 | B222: Bedmutha Industries Ltd | G222: https://www.bseindia.com/stock-share-price/Bedmutha-Industries-Ltd/518017/

Sheet PE Band DETAIL v8
A1: Sr No | B1: BSE Code | C1: Company Name | D1: Calendar Year | E1: CMP TODAY All Years | F1: EPS (Rs) | G1: EPS Source | H1: Year High | I1: Year Low | J1: High PE Formula | K1: Low PE Formula | L1: Confidence Flag | M1: PE High | N1: PE Low | O1: BSE_CMP_Official_LIVE | P1: BSE_52W_High_Official | Q1: BSE_52W_Low_Official | R1: CMP_Match_Status | S1: Final_CMP_AutoCorrected | T1: Last_Verified_IST
A2: 4 | B2: 500008 | C2: Amara Raja Energy & Mobility Ltd | D2: 2015 | E2: 874.45001 | G2: Consolidated first (v4) – needs verification for flagged rows | H2: 1132 | I2: 778 | L2: INCOMPLETE | O2: 882.5 | P2: 1057.85 | Q2: 670 | R2: VERIFIED_OK | S2: 882.5 | T2: 30-07-2026 09:42 IST
A3: 4 | B3: 500008 | C3: Amara Raja Energy & Mobility Ltd | D3: 2016 | E3: 874.45001 | G3: Consolidated first (v4) – needs verification for flagged rows | H3: 1077 | I3: 773.05 | L3: INCOMPLETE | O3: 882.5 | P3: 1057.85 | Q3: 670 | R3: VERIFIED_OK | S3: 882.5 | T3: 30-07-2026 09:42 IST
A4: 4 | B4: 500008 | C4: Amara Raja Energy & Mobility Ltd | D4: 2017 | E4: 874.45001 | G4: Consolidated first (v4) – needs verification for flagged rows | H4: 954.54999 | I4: 665.45001 | L4: INCOMPLETE | O4: 882.5 | P4: 1057.85 | Q4: 670 | R4: VERIFIED_OK | S4: 882.5 | T4: 30-07-2026 09:42 IST
A5: 4 | B5: 500008 | C5: Amara Raja Energy & Mobility Ltd | D5: 2018 | E5: 874.45001 | G5: Consolidated first (v4) – needs verification for flagged rows | H5: 907.75 | I5: 670.65002 | L5: INCOMPLETE | O5: 882.5 | P5: 1057.85 | Q5: 670 | R5: VERIFIED_OK | S5: 882.5 | T5: 30-07-2026 09:42 IST
A6: 4 | B6: 500008 | C6: Amara Raja Energy & Mobility Ltd | D6: 2019 | E6: 874.45001 | F6: 28.29 | G6: Consolidated first (v4) – needs verification for flagged rows | H6: 796 | I6: 572.59998 | L6: OK | M6: 28.14 | N6: 20.24 | O6: 882.5 | P6: 1057.85 | Q6: 670 | R6: VERIFIED_OK | S6: 882.5 | T6: 30-07-2026 09:42 IST
A7: 4 | B7: 500008 | C7: Amara Raja Energy & Mobility Ltd | D7: 2020 | E7: 874.45001 | F7: 38.69 | G7: Consolidated first (v4) – needs verification for flagged rows | H7: 963.95001 | I7: 350.25 | L7: OK | M7: 24.91 | N7: 9.05 | O7: 882.5 | P7: 1057.85 | Q7: 670 | R7: VERIFIED_OK | S7: 882.5 | T7: 30-07-2026 09:42 IST
A8: 4 | B8: 500008 | C8: Amara Raja Energy & Mobility Ltd | D8: 2021 | E8: 874.45001 | F8: 37.87 | G8: Consolidated first (v4) – needs verification for flagged rows | H8: 1025 | I8: 584.45001 | L8: OK | M8: 27.07 | N8: 15.43 | O8: 882.5 | P8: 1057.85 | Q8: 670 | R8: VERIFIED_OK | S8: 882.5 | T8: 30-07-2026 09:42 IST
A9: 4 | B9: 500008 | C9: Amara Raja Energy & Mobility Ltd | D9: 2022 | E9: 874.45001 | F9: 30.01 | G9: Consolidated first (v4) – needs verification for flagged rows | H9: 669.95001 | I9: 445.39999 | L9: OK | M9: 22.32 | N9: 14.84 | O9: 882.5 | P9: 1057.85 | Q9: 670 | R9: VERIFIED_OK | S9: 882.5 | T9: 30-07-2026 09:42 IST
A10: 4 | B10: 500008 | C10: Amara Raja Energy & Mobility Ltd | D10: 2023 | E10: 874.45001 | F10: 42.79 | G10: Consolidated first (v4) – needs verification for flagged rows | H10: 831.25 | I10: 546.54999 | L10: OK | M10: 19.43 | N10: 12.77 | O10: 882.5 | P10: 1057.85 | Q10: 670 | R10: VERIFIED_OK | S10: 882.5 | T10: 30-07-2026 09:42 IST
A11: 4 | B11: 500008 | C11: Amara Raja Energy & Mobility Ltd | D11: 2024 | E11: 874.45001 | F11: 51.05 | G11: Consolidated first (v4) – needs verification for flagged rows | H11: 1774.9 | I11: 737.65002 | L11: OK | M11: 34.77 | N11: 14.45 | O11: 882.5 | P11: 1057.85 | Q11: 670 | R11: VERIFIED_OK | S11: 882.5 | T11: 30-07-2026 09:42 IST
A12: 4 | B12: 500008 | C12: Amara Raja Energy & Mobility Ltd | D12: 2025 | E12: 874.45001 | F12: 51.61 | G12: Consolidated first (v4) – needs verification for flagged rows | H12: 1220 | I12: 805.04999 | L12: OK | M12: 23.64 | N12: 15.6 | O12: 882.5 | P12: 1057.85 | Q12: 670 | R12: VERIFIED_OK | S12: 882.5 | T12: 30-07-2026 09:42 IST
A13: 4 | B13: 500008 | C13: Amara Raja Energy & Mobility Ltd | D13: 2026 | E13: 874.45001 | F13: 48.94 | G13: Consolidated first (v4) – needs verification for flagged rows | H13: 957.45001 | I13: 671.45001 | L13: OK | M13: 19.56 | N13: 13.72 | O13: 882.5 | P13: 1057.85 | Q13: 670 | R13: VERIFIED_OK | S13: 882.5 | T13: 30-07-2026 09:42 IST
A14: 6 | B14: 500034 | C14: Bajaj Finance Ltd | D14: 2015 | E14: 1055.7 | F14: 1.79 | G14: Consolidated first (v4) – needs verification for flagged rows | H14: 60.439999 | I14: 33.945999 | L14: OK | M14: 33.77 | N14: 18.96 | O14: 1054.8 | P14: 1102.5 | Q14: 787.9 | R14: VERIFIED_OK | S14: 1054.8 | T14: 30-07-2026 09:42 IST
A15: 6 | B15: 500034 | C15: Bajaj Finance Ltd | D15: 2016 | E15: 1055.7 | F15: 2.37 | G15: Consolidated first (v4) – needs verification for flagged rows | H15: 118 | I15: 53.5 | L15: OK | M15: 49.79 | N15: 22.57 | O15: 1054.8 | P15: 1102.5 | Q15: 787.9 | R15: VERIFIED_OK | S15: 1054.8 | T15: 30-07-2026 09:42 IST
A16: 6 | B16: 500034 | C16: Bajaj Finance Ltd | D16: 2017 | E16: 1055.7 | F16: 3.34 | G16: Consolidated first (v4) – needs verification for flagged rows | H16: 198.89999 | I16: 86 | L16: OK | M16: 59.55 | N16: 25.75 | O16: 1054.8 | P16: 1102.5 | Q16: 787.9 | R16: VERIFIED_OK | S16: 1054.8 | T16: 30-07-2026 09:42 IST
A17: 6 | B17: 500034 | C17: Bajaj Finance Ltd | D17: 2018 | E17: 1055.7 | F17: 4.32 | G17: Consolidated first (v4) – needs verification for flagged rows | H17: 299.51001 | I17: 151.44 | L17: OK | M17: 69.33 | N17: 35.06 | O17: 1054.8 | P17: 1102.5 | Q17: 787.9 | R17: VERIFIED_OK | S17: 1054.8 | T17: 30-07-2026 09:42 IST
... A32: 10 | B32: 500055 | C32: Bombay Dyeing | D32: 2021 | E32: 85.550003 | F32: -0.48 | G32: Consolidated first (v4) – needs verification for flagged rows | H32: 109.6 | I32: 37.400002 | L32: INCOMPLETE | M32: -228.33 | N32: -77.92 | O32: 1776.8 | P32: 2110 | Q32: 1322.5 | R32: MISMATCH_NEEDS_CORRECTION | S32: 1776.8 | T32: 30-07-2026 09:42 IST
A33: 11 | B33: 500059 | C33: Birla Power Solutions Ltd | D33: 2015 | E33: 4.0500002 | F33: -216.28 | G33: Consolidated first (v4) – needs verification for flagged rows | H33: 120.8 | I33: 69 | L33: UNVERIFIED – negative EPS | M33: -0.56 | N33: -0.32 | O33: =IFERROR(VLOOKUP(B33,BSE_500_LIVE!A:E,3,FALSE),"") | P33: =IFERROR(VLOOKUP(B33,BSE_500_LIVE!A:E,4,FALSE),"") | Q33: =IFERROR(VLOOKUP(B33,BSE_500_LIVE!A:E,5,FALSE),"") | R33: =IF(OR(E33="",O33=""),"PENDING_FETCH",IF(ABS(E33-O33)/E33>0.005,"MISMATCH_NEEDS_CORRECTION","VERIFIED_OK")) | S33: =IF(O33<>"",O33,E33) | T33: =IFERROR(VLOOKUP(B33,BSE_500_LIVE!A:F,6,FALSE),"")
A34: 11 | B34: 500059 | C34: Birla Power Solutions Ltd | D34: 2016 | E34: 4.0500002 | F34: -140.85 | G34: Consolidated first (v4) – needs verification for flagged rows | H34: 120.9 | I34: 50 | L34: UNVERIFIED – negative EPS | M34: -0.86 | N34: -0.35 | O34: =IFERROR(VLOOKUP(B34,BSE_500_LIVE!A:E,3,FALSE),"") | P34: =IFERROR(VLOOKUP(B34,BSE_500_LIVE!A:E,4,FALSE),"") | Q34: =IFERROR(VLOOKUP(B34,BSE_500_LIVE!A:E,5,FALSE),"") | R34: =IF(OR(E34="",O34=""),"PENDING_FETCH",IF(ABS(E34-O34)/E34>0.005,"MISMATCH_NEEDS_CORRECTION","VERIFIED_OK")) | S34: =IF(O34<>"",O34,E34) | T34: =IFERROR(VLOOKUP(B34,BSE_500_LIVE!A:F,6,FALSE),"")
A35: 11 | B35: 500059 | C35: Birla Power Solutions Ltd | D35: 2017 | E35: 4.0500002 | F35: -146.95 | G35: Consolidated first (v4) – needs verification for flagged rows | H35: 149.39999 | I35: 67.050003 | L35: UNVERIFIED – negative EPS | M35: -1.02 | N35: -0.46 | O35: =IFERROR(VLOOKUP(B35,BSE_500_LIVE!A:E,3,FALSE),"") | P35: =IFERROR(VLOOKUP(B35,BSE_500_LIVE!A:E,4,FALSE),"") | Q35: =IFERROR(VLOOKUP(B35,BSE_500_LIVE!A:E,5,FALSE),"") | R35: =IF(OR(E35="",O35=""),"PENDING_FETCH",IF(ABS(E35-O35)/E35>0.005,"MISMATCH_NEEDS_CORRECTION","VERIFIED_OK")) | S35: =IF(O35<>"",O35,E35) | T35: =IFERROR(VLOOKUP(B35,BSE_500_LIVE!A:F,6,FALSE),"")
A36: 11 | B36: 500059 | C36: Birla Power Solutions Ltd | D36: 2018 | E36: 4.0500002 | F36: 8.33 | G36: Consolidated first (v4) – needs verification for flagged rows | H36: 152.8 | I36: 64.199997 | L36: OK | M36: 18.34 | N36: 7.71 | O36: =IFERROR(VLOOKUP(B36,BSE_500_LIVE!A:E,3,FALSE),"") | P36: =IFERROR(VLOOKUP(B36,BSE_500_LIVE!A:E,4,FALSE),"") | Q36: =IFERROR(VLOOKUP(B36,BSE_500_LIVE!A:E,5,FALSE),"") | R36: =IF(OR(E36="",O36=""),"PENDING_FETCH",IF(ABS(E36-O36)/E36>0.005,"MISMATCH_NEEDS_CORRECTION","VERIFIED_OK")) | S36: =IF(O36<>"",O36,E36) | T36: =IFERROR(VLOOKUP(B36,BSE_500_LIVE!A:F,6,FALSE),"")
A37: 11 | B37: 500059 | C37: Birla Power Solutions Ltd | D37: 2019 | E37: 4.0500002 | F37: 347.49 | G37: Consolidated first (v4) – needs verification for flagged rows | H37: 75 | I37: 5.4299998 | L37: OK | M37: 0.22 | N37: 0.02 | O37: =IFERROR(VLOOKUP(B37,BSE_500_LIVE!A:E,3,FALSE),"") | P37: =IFERROR(VLOOKUP(B37,BSE_500_LIVE!A:E,4,FALSE),"") | Q37: =IFERROR(VLOOKUP(B37,BSE_500_LIVE!A:E,5,FALSE),"") | R37: =IF(OR(E37="",O37=""),"PENDING_FETCH",IF(ABS(E37-O37)/E37>0.005,"MISMATCH_NEEDS_CORRECTION","VERIFIED_OK")) | S37: =IF(O37<>"",O37,E37) | T37: =IFERROR(VLOOKUP(B37,BSE_500_LIVE!A:F,6,FALSE),"")
A38: 11 | B38: 500059 | C38: Birla Power Solutions Ltd | D38: 2020 | E38: 4.0500002 | F38: -395.75 | G38: Consolidated first (v4) – needs verification for flagged rows | H38: 8.6499996 | I38: 5.4699998 | L38: UNVERIFIED – negative EPS | M38: -0.02 | N38: -0.01 | O38: =IFERROR(VLOOKUP(B38,BSE_500_LIVE!A:E,3,FALSE),"") | P38: =IFERROR(VLOOKUP(B38,BSE_500_LIVE!A:E,4,FALSE),"") | Q38: =IFERROR(VLOOKUP(B38,BSE_500_LIVE!A:E,5,FALSE),"") | R38: =IF(OR(E38="",O38=""),"PENDING_FETCH",IF(ABS(E38-O38)/E38>0.005,"MISMATCH_NEEDS_CORRECTION","VERIFIED_OK")) | S38: =IF(O38<>"",O38,E38) | T38: =IFERROR(VLOOKUP(B38,BSE_500_LIVE!A:F,6,FALSE),"")
A39: 11 | B39: 500059 | C39: Birla Power Solutions Ltd | D39: 2021 | E39: 4.0500002 | F39: 93.36 | G39: Consolidated first (v4) – needs verification for flagged rows | H39: 5.5 | I39: 5.5 | L39: OK | M39: 0.06 | N39: 0.06 | O39: =IFERROR(VLOOKUP(B39,BSE_500_LIVE!A:E,3,FALSE),"") | P39: =IFERROR(VLOOKUP(B39,BSE_500_LIVE!A:E,4,FALSE),"") | Q39: =IFERROR(VLOOKUP(B39,BSE_500_LIVE!A:E,5,FALSE),"") | R39: =IF(OR(E39="",O39=""),"PENDING_FETCH",IF(ABS(E39-O39)/E39>0.005,"MISMATCH_NEEDS_CORRECTION","VERIFIED_OK")) | S39: =IF(O39<>"",O39,E39) | T39: =IFERROR(VLOOKUP(B39,BSE_500_LIVE!A:F,6,FALSE),"")
A40: 11 | B40: 500059 | C40: Birla Power Solutions Ltd | D40: 2022 | E40: 4.0500002 | F40: 56.89 | G40: Consolidated first (v4) – needs verification for flagged rows | H40: 5.5 | I40: 5.5 | L40: OK | M40: 0.1 | N40: 0.1 | O40: =IFERROR(VLOOKUP(B40,BSE_500_LIVE!A:E,3,FALSE),"") | P40: =IFERROR(VLOOKUP(B40,BSE_500_LIVE!A:E,4,FALSE),"") | Q40: =IFERROR(VLOOKUP(B40,BSE_500_LIVE!A:E,5,FALSE),"") | R40: =IF(OR(E40="",O40=""),"PENDING_FETCH",IF(ABS(E40-O40)/E40>0.005,"MISMATCH_NEEDS_CORRECTION","VERIFIED_OK")) | S40: =IF(O40<>"",O40,E40) | T40: =IFERROR(VLOOKUP(B40,BSE_500_LIVE!A:F,6,FALSE),"")
A41: 11 | B41: 500059 | C41: Birla Power Solutions Ltd | D41: 2023 | E41: 4.0500002 | F41: -48.05 | G41: Consolidated first (v4) – needs verification for flagged rows | H41: 36.490002 | I41: 5.5 | L41: UNVERIFIED – negative EPS | M41: -0.76 | N41: -0.11 | O41: =IFERROR(VLOOKUP(B41,BSE_500_LIVE!A:E,3,FALSE),"") | P41: =IFERROR(VLOOKUP(B41,BSE_500_LIVE!A:E,4,FALSE),"") | Q41: =IFERROR(VLOOKUP(B41,BSE_500_LIVE!A:E,5,FALSE),"") | R41: =IF(OR(E41="",O41=""),"PENDING_FETCH",IF(ABS(E41-O41)/E41>0.005,"MISMATCH_NEEDS_CORRECTION","VERIFIED_OK")) | S41: =IF(O41<>"",O41,E41) | T41: =IFERROR(VLOOKUP(B41,BSE_500_LIVE!A:F,6,FALSE),"")
A42: 11 | B42: 500059 | C42: Birla Power Solutions Ltd | D42: 2024 | E42: 4.0500002 | F42: -2.28 | G42: Consolidated first (v4) – needs verification for flagged rows | H42: 22.1 | I42: 13.22 | L42: UNVERIFIED – negative EPS | M42: -9.69 | N42: -5.8 | O42: =IFERROR(VLOOKUP(B42,BSE_500_LIVE!A:E,3,FALSE),"") | P42: =IFERROR(VLOOKUP(B42,BSE_500_LIVE!A:E,4,FALSE),"") | Q42: =IFERROR(VLOOKUP(B42,BSE_500_LIVE!A:E,5,FALSE),"") | R42: =IF(OR(E42="",O42=""),"PENDING_FETCH",IF(ABS(E42-O42)/E42>0.005,"MISMATCH_NEEDS_CORRECTION","VERIFIED_OK")) | S42: =IF(O42<>"",O42,E42) | T42: =IFERROR(VLOOKUP(B42,BSE_500_LIVE!A:F,6,FALSE),"")
A43: 11 | B43: 500059 | C43: Birla Power Solutions Ltd | D43: 2025 | E43: 4.0500002 | F43: 2.18 | G43: Consolidated first (v4) – needs verification for flagged rows | H43: 23.559999 | I43: 6.6599998 | L43: OK | M43: 10.81 | N43: 3.06 | O43: =IFERROR(VLOOKUP(B43,BSE_500_LIVE!A:E,3,FALSE),"") | P43: =IFERROR(VLOOKUP(B43,BSE_500_LIVE!A:E,4,FALSE),"") | Q43: =IFERROR(VLOOKUP(B43,BSE_500_LIVE!A:E,5,FALSE),"") | R43: =IF(OR(E43="",O43=""),"PENDING_FETCH",IF(ABS(E43-O43)/E43>0.005,"MISMATCH_NEEDS_CORRECTION","VERIFIED_OK")) | S43: =IF(O43<>"",O43,E43) | T43: =IFERROR(VLOOKUP(B43,BSE_500_LIVE!A:F,6,FALSE),"")
A44: 11 | B44: 500059 | C44: Birla Power Solutions Ltd | D44: 2026 | E44: 4.0500002 | F44: -0.01 | G44: Consolidated first (v4) – needs verification for flagged rows | H44: 7.6500001 | I44: 3.8199999 | L44: UNVERIFIED – negative EPS | M44: -765 | N44: -382 | O44: =IFERROR(VLOOKUP(B44,BSE_500_LIVE!A:E,3,FALSE),"") | P44: =IFERROR(VLOOKUP(B44,BSE_500_LIVE!A:E,4,FALSE),"") | Q44: =IFERROR(VLOOKUP(B44,BSE_500_LIVE!A:E,5,FALSE),"") | R44: =IF(OR(E44="",O44=""),"PENDING_FETCH",IF(ABS(E44-O44)/E44>0.005,"MISMATCH_NEEDS_CORRECTION","VERIFIED_OK")) | S44: =IF(O44<>"",O44,E44) | T44: =IFERROR(VLOOKUP(B44,BSE_500_LIVE!A:F,6,FALSE),"")
A45: 13 | B45: 500089 | C45: Dichloromethane | D45: 2015 | E45: 512.90002 | G45: Consolidated first (v4) – needs verification for flagged rows | H45: 746.75 | L45: INCOMPLETE | O45: =IFERROR(VLOOKUP(B45,BSE_500_LIVE!A:E,3,FALSE),"") | P45: =IFERROR(VLOOKUP(B45,BSE_500_LIVE!A:E,4,FALSE),"") | Q45: =IFERROR(VLOOKUP(B45,BSE_500_LIVE!A:E,5,FALSE),"") | R45: =IF(OR(E45="",O45=""),"PENDING_FETCH",IF(ABS(E45-O45)/E45>0.005,"MISMATCH_NEEDS_CORRECTION","VERIFIED_OK")) | S45: =IF(O45<>"",O45,E45) | T45: =IFERROR(VLOOKUP(B45,BSE_500_LIVE!A:F,6,FALSE),"")
A46: 13 | B46: 500089 | C46: Dichloromethane | D46: 2016 | E46: 512.90002 | G46: Consolidated first (v4) – needs verification for flagged rows | H46: 745.75 | I46: 443 | L46: INCOMPLETE | O46: =IFERROR(VLOOKUP(B46,BSE_500_LIVE!A:E,3,FALSE),"") | P46: =IFERROR(VLOOKUP(B46,BSE_500_LIVE!A:E,4,FALSE),"") | Q46: =IFERROR(VLOOKUP(B46,BSE_500_LIVE!A:E,5,FALSE),"") | R46: =IF(OR(E46="",O46=""),"PENDING_FETCH",IF(ABS(E46-O46)/E46>0.005,"MISMATCH_NEEDS_CORRECTION","VERIFIED_OK")) | S46: =IF(O46<>"",O46,E46) | T46: =IFERROR(VLOOKUP(B46,BSE_500_LIVE!A:F,6,FALSE),"")
A47: 13 | B47: 500089 | C47: Dichloromethane | D47: 2017 | E47: 512.90002 | G47: Consolidated first (v4) – needs verification for flagged rows | H47: 605 | I47: 432.64999 | L47: INCOMPLETE | O47: =IFERROR(VLOOKUP(B47,BSE_500_LIVE!A:E,3,FALSE),"") | P47: =IFERROR(VLOOKUP(B47,BSE_500_LIVE!A:E,4,FALSE),"") | Q47: =IFERROR(VLOOKUP(B47,BSE_500_LIVE!A:E,5,FALSE),"") | R47: =IF(OR(E47="",O47=""),"PENDING_FETCH",IF(ABS(E47-O47)/E47>0.005,"MISMATCH_NEEDS_CORRECTION","VERIFIED_OK")) | S47: =IF(O47<>"",O47,E47) | T47: =IFERROR(VLOOKUP(B47,BSE_500_LIVE!A:F,6,FALSE),"")
A48: 13 | B48: 500089 | C48: Dichloromethane | D48: 2018 | E48: 512.90002 | G48: Consolidated first (v4) – needs verification for flagged rows | H48: 635 | I48: 332 | L48: INCOMPLETE | O48: =IFERROR(VLOOKUP(B48,BSE_500_LIVE!A:E,3,FALSE),"") | P48: =IFERROR(VLOOKUP(B48,BSE_500_LIVE!A:E,4,FALSE),"") | Q48: =IFERROR(VLOOKUP(B48,BSE_500_LIVE!A:E,5,FALSE),"") | R48: =IF(OR(E48="",O48=""),"PENDING_FETCH",IF(ABS(E48-O48)/E48>0.005,"MISMATCH_NEEDS_CORRECTION","VERIFIED_OK")) | S48: =IF(O48<>"",O48,E48) | T48: =IFERROR(VLOOKUP(B48,BSE_500_LIVE!A:F,6,FALSE),"")
A49: 13 | B49: 500089 | C49: Dichloromethane | D49: 2019 | E49: 512.90002 | G49: Consolidated first (v4) – needs verification for flagged rows | H49: 424 | I49: 294.10001 | L49: INCOMPLETE | O49: =IFERROR(VLOOKUP(B49,BSE_500_LIVE!A:E,3,FALSE),"") | P49: =IFERROR(VLOOKUP(B49,BSE_500_LIVE!A:E,4,FALSE),"") | Q49: =IFERROR(VLOOKUP(B49,BSE_500_LIVE!A:E,5,FALSE),"") | R49: =IF(OR(E49="",O49=""),"PENDING_FETCH",IF(ABS(E49-O49)/E49>0.005,"MISMATCH_NEEDS_CORRECTION","VERIFIED_OK")) | S49: =IF(O49<>"",O49,E49) | T49: =IFERROR(VLOOKUP(B49,BSE_500_LIVE!A:F,6,FALSE),"")
A50: 13 | B50: 500089 | C50: Dichloromethane | D50: 2020 | E50: 512.90002 | G50: Consolidated first (v4) – needs verification for flagged rows | H50: 450 | I50: 242 | L50: INCOMPLETE | O50: =IFERROR(VLOOKUP(B50,BSE_500_LIVE!A:E,3,FALSE),"") | P50: =IFERROR(VLOOKUP(B50,BSE_500_LIVE!A:E,4,FALSE),"") | Q50: =IFERROR(VLOOKUP(B50,BSE_500_LIVE!A:E,5,FALSE),"") | R50: =IF(OR(E50="",O50=""),"PENDING_FETCH",IF(ABS(E50-O50)/E50>0.005,"MISMATCH_NEEDS_CORRECTION","VERIFIED_OK")) | S50: =IF(O50<>"",O50,E50) | T50: =IFERROR(VLOOKUP(B50,BSE_500_LIVE!A:F,6,FALSE),"")
A51: 13 | B51: 500089 | C51: Dichloromethane | D51: 2021 | E51: 512.90002 | G51: Consolidated first (v4) – needs verification for flagged rows | H51: 549 | I51: 367.5 | L51: INCOMPLETE | O51: =IFERROR(VLOOKUP(B51,BSE_500_LIVE!A:E,3,FALSE),"") | P51: =IFERROR(VLOOKUP(B51,BSE_500_LIVE!A:E,4,FALSE),"") | Q51: =IFERROR(VLOOKUP(B51,BSE_500_LIVE!A:E,5,FALSE),"") | R51: =IF(OR(E51="",O51=""),"PENDING_FETCH",IF(ABS(E51-O51)/E51>0.005,"MISMATCH_NEEDS_CORRECTION","VERIFIED_OK")) | S51: =IF(O51<>"",O51,E51) | T51: =IFERROR(VLOOKUP(B51,BSE_500_LIVE!A:F,6,FALSE),"")
A52: 13 | B52: 500089 | C52: Dichloromethane | D52: 2022 | E52: 512.90002 | G52: Consolidated first (v4) – needs verification for flagged rows | H52: 493.85001 | I52: 321 | L52: INCOMPLETE | O52: =IFERROR(VLOOKUP(B52,BSE_500_LIVE!A:E,3,FALSE),"") | P52: =IFERROR(VLOOKUP(B52,BSE_500_LIVE!A:E,4,FALSE),"") | Q52: =IFERROR(VLOOKUP(B52,BSE_500_LIVE!A:E,5,FALSE),"") | R52: =IF(OR(E52="",O52=""),"PENDING_FETCH",IF(ABS(E52-O52)/E52>0.005,"MISMATCH_NEEDS_CORRECTION","VERIFIED_OK")) | S52: =IF(O52<>"",O52,E52) | T52: =IFERROR(VLOOKUP(B52,BSE_500_LIVE!A:F,6,FALSE),"")
A53: 13 | B53: 500089 | C53: Dichloromethane | D53: 2023 | E53: 512.90002 | G53: Consolidated first (v4) – needs verification for flagged rows | H53: 544 | I53: 366 | L53: INCOMPLETE | O53: =IFERROR(VLOOKUP(B53,BSE_500_LIVE!A:E,3,FALSE),"") | P53: =IFERROR(VLOOKUP(B53,BSE_500_LIVE!A:E,4,FALSE),"") | Q53: =IFERROR(VLOOKUP(B53,BSE_500_LIVE!A:E,5,FALSE),"") | R53: =IF(OR(E53="",O53=""),"PENDING_FETCH",IF(ABS(E53-O53)/E53>0.005,"MISMATCH_NEEDS_CORRECTION","VERIFIED_OK")) | S53: =IF(O53<>"",O53,E53) | T53: =IFERROR(VLOOKUP(B53,BSE_500_LIVE!A:F,6,FALSE),"")
A54: 13 | B54: 500089 | C54: Dichloromethane | D54: 2024 | E54: 512.90002 | G54: Consolidated first (v4) – needs verification for flagged rows | H54: 833 | I54: 414.20001 | L54: INCOMPLETE | O54: =IFERROR(VLOOKUP(B54,BSE_500_LIVE!A:E,3,FALSE),"") | P54: =IFERROR(VLOOKUP(B54,BSE_500_LIVE!A:E,4,FALSE),"") | Q54: =IFERROR(VLOOKUP(B54,BSE_500_LIVE!A:E,5,FALSE),"") | R54: =IF(OR(E54="",O54=""),"PENDING_FETCH",IF(ABS(E54-O54)/E54>0.005,"MISMATCH_NEEDS_CORRECTION","VERIFIED_OK")) | S54: =IF(O54<>"",O54,E54) | T54: =IFERROR(VLOOKUP(B54,BSE_500_LIVE!A:F,6,FALSE),"")
A55: 13 | B55: 500089 | C55: Dichloromethane | D55: 2025 | E55: 512.90002 | G55: Consolidated first (v4) – needs verification for flagged rows | H55: 739.90002 | I55: 467.60001 | L55: INCOMPLETE | O55: =IFERROR(VLOOKUP(B55,BSE_500_LIVE!A:E,3,FALSE),"") | P55: =IFERROR(VLOOKUP(B55,BSE_500_LIVE!A:E,4,FALSE),"") | Q55: =IFERROR(VLOOKUP(B55,BSE_500_LIVE!A:E,5,FALSE),"") | R55: =IF(OR(E55="",O55=""),"PENDING_FETCH",IF(ABS(E55-O55)/E55>0.005,"MISMATCH_NEEDS_CORRECTION","VERIFIED_OK")) | S55: =IF(O55<>"",O55,E55) | T55: =IFERROR(VLOOKUP(B55,BSE_500_LIVE!A:F,6,FALSE),"")
A56: 13 | B56: 500089 | C56: Dichloromethane | D56: 2026 | E56: 512.90002 | G56: Consolidated first (v4) – needs verification for flagged rows | H56: 619.95001 | I56: 452 | L56: INCOMPLETE | O56: =IFERROR(VLOOKUP(B56,BSE_500_LIVE!A:E,3,FALSE),"") | P56: =IFERROR(VLOOKUP(B56,BSE_500_LIVE!A:E,4,FALSE),"") | Q56: =IFERROR(VLOOKUP(B56,BSE_500_LIVE!A:E,5,FALSE),"") | R56: =IF(OR(E56="",O56=""),"PENDING_FETCH",IF(ABS(E56-O56)/E56>0.005,"MISMATCH_NEEDS_CORRECTION","VERIFIED_OK")) | S56: =IF(O56<>"",O56,E56) | T56: =IFERROR(VLOOKUP(B56,BSE_500_LIVE!A:F,6,FALSE),"")
A57: 16 | B57: 500112 | C57: State Bank Of India | D57: 2015 | E57: 1044.1 | F57: 17.55 | G57: Consolidated first (v4) – needs verification for flagged rows | H57: 335.89999 | I57: 221.25 | L57: VERIFIED – Corrected from 22.76 to 17.55 – Source: SBI Annual Reports + Screener consolidated – FY17 10,484cr profit / 797cr shares... | M57: 19.14 | N57: 12.61 | O57: 1010.8 | P57: 1234.7 | Q57: 786.55 | R57: VERIFIED_OK | S57: 1010.8 | T57: 30-07-2026 09:42 IST
A58: 16 | B58: 500112 | C58: State Bank Of India | D58: 2016 | E58: 1044.1 | F58: 12.82 | G58: Consolidated first (v4) – needs verification for flagged rows | H58: 288.5 | I58: 148.3 | L58: VERIFIED – Corrected from 15.75 to 12.82 – Source: SBI Annual Reports + Screener consolidated – FY17 10,484cr profit / 797cr shares... | M58: 22.5 | N58: 11.57 | O58: 1010.8 | P58: 1234.7 | Q58: 786.55 | R58: VERIFIED_OK | S58: 1010.8 | T58: 30-07-2026 09:42 IST
A59: 16 | B59: 500112 | C59: State Bank Of India | D59: 2017 | E59: 1044.1 | F59: 13.15 | G59: Consolidated first (v4) – needs verification for flagged rows | H59: 351.5 | I59: 241.10001 | L59: VERIFIED – Corrected from 0.3 to 13.15 – Source: SBI Annual Reports + Screener consolidated – FY17 10,484cr profit / 797cr shares... | M59: 26.73 | N59: 18.33 | O59: 1010.8 | P59: 1234.7 | Q59: 786.55 | R59: VERIFIED_OK | S59: 1010.8 | T59: 30-07-2026 09:42 IST
A60: 16 | B60: 500112 | C60: State Bank Of India | D60: 2018 | E60: 1044.1 | F60: -7.34 | G60: Consolidated first (v4) – needs verification for flagged rows | H60: 334.79999 | I60: 232 | L60: VERIFIED – Corrected from -5.11 to -7.34 – Source: SBI Annual Reports + Screener consolidated – FY17 10,484cr profit / 797cr shares... | M60: -45.61 | N60: -31.61 | O60: 1010.8 | P60: 1234.7 | Q60: 786.55 | R60: VERIFIED_OK | S60: 1010.8 | T60: 30-07-2026 09:42 IST
A61: 16 | B61: 500112 | C61: State Bank Of India | D61: 2019 | E61: 1044.1 | F61: 1 | G61: Consolidated first (v4) – needs verification for flagged rows | H61: 373.70001 | I61: 244.35001 | L61: VERIFIED – Corrected from 2.58 to 1.0 – Source: SBI Annual Reports + Screener consolidated – FY17 10,484cr profit / 797cr shares... | M61: 373.7 | N61: 244.35 | O61: 1010.8 | P61: 1234.7 | Q61: 786.55 | R61: VERIFIED_OK | S61: 1010.8 | T61: 30-07-2026 09:42 IST
A62: 16 | B62: 500112 | C62: State Bank Of India | D62: 2020 | E62: 1044.1 | F62: 16 | G62: Consolidated first (v4) – needs verification for flagged rows | H62: 339.85001 | I62: 149.55 | L62: VERIFIED – Corrected from 22.15 to 16.0 – Source: SBI Annual Reports + Screener consolidated – FY17 10,484cr profit / 797cr shares... | M62: 21.24 | N62: 9.35 | O62: 1010.8 | P62: 1234.7 | Q62: 786.55 | R62: VERIFIED_OK | S62: 1010.8 | T62: 30-07-2026 09:42 IST
A63: 16 | B63: 500112 | C63: State Bank Of India | D63: 2021 | E63: 1044.1 | F63: 23 | G63: Consolidated first (v4) – needs verification for flagged rows | H63: 542.20001 | I63: 269.54999 | L63: VERIFIED – Corrected from 25.11 to 23.0 – Source: SBI Annual Reports + Screener consolidated – FY17 10,484cr profit / 797cr shares... | M63: 23.57 | N63: 11.72 | O63: 1010.8 | P63: 1234.7 | Q63: 786.55 | R63: VERIFIED_OK | S63: 1010.8 | T63: 30-07-2026 09:42 IST
A64: 16 | B64: 500112 | C64: State Bank Of India | D64: 2022 | E64: 1044.1 | F64: 38 | G64: Consolidated first (v4) – needs verification for flagged rows | H64: 629.65002 | I64: 425 | L64: VERIFIED – Corrected from 39.64 to 38.0 – Source: SBI Annual Reports + Screener consolidated – FY17 10,484cr profit / 797cr shares... | M64: 16.57 | N64: 11.18 | O64: 1010.8 | P64: 1234.7 | Q64: 786.55 | R64: VERIFIED_OK | S64: 1010.8 | T64: 30-07-2026 09:42 IST
A65: 16 | B65: 500112 | C65: State Bank Of India | D65: 2023 | E65: 1044.1 | F65: 56 | G65: Consolidated first (v4) – needs verification for flagged rows | H65: 660.40002 | I65: 499.35001 | L65: VERIFIED – Corrected from 62.35 to 56.0 – Source: SBI Annual Reports + Screener consolidated – FY17 10,484cr profit / 797cr shares... | M65: 11.79 | N65: 8.92 | O65: 1010.8 | P65: 1234.7 | Q65: 786.55 | R65: VERIFIED_OK | S65: 1010.8 | T65: 30-07-2026 09:42 IST
A66: 16 | B66: 500112 | C66: State Bank Of India | D66: 2024 | E66: 1044.1 | F66: 75 | G66: Consolidated first (v4) – needs verification for flagged rows | H66: 912.09998 | I66: 600.70001 | L66: VERIFIED – Corrected from 75.17 to 75.0 – Source: SBI Annual Reports + Screener consolidated – FY17 10,484cr profit / 797cr shares... | M66: 12.16 | N66: 8.01 | O66: 1010.8 | P66: 1234.7 | Q66: 786.55 | R66: VERIFIED_OK | S66: 1010.8 | T66: 30-07-2026 09:42 IST
A67: 16 | B67: 500112 | C67: State Bank Of India | D67: 2025 | E67: 1044.1 | F67: 80 | G67: Consolidated first (v4) – needs verification for flagged rows | H67: 999.09998 | I67: 679.65002 | L67: VERIFIED – Corrected from 86.91 to 80.0 – Source: SBI Annual Reports + Screener consolidated – FY17 10,484cr profit / 797cr shares... | M67: 12.49 | N67: 8.5 | O67: 1010.8 | P67: 1234.7 | Q67: 786.55 | R67: VERIFIED_OK | S67: 1010.8 | T67: 30-07-2026 09:42 IST
A68: 16 | B68: 500112 | C68: State Bank Of India | D68: 2026 | E68: 1044.1 | F68: 85 | G68: Consolidated first (v4) – needs verification for flagged rows | H68: 1234.8 | I68: 933.84998 | L68: VERIFIED – Corrected from 90.24 to 85.0 – Source: SBI Annual Reports + Screener consolidated – FY17 10,484cr profit / 797cr shares... | M68: 14.53 | N68: 10.99 | O68: 1010.8 | P68: 1234.7 | Q68: 786.55 | R68: VERIFIED_OK | S68: 1010.8 | T68: 30-07-2026 09:42 IST
... A116: 27 | B116: 500170 | C116: National Chemicals | D116: 2026 | E116: 24.98 | F116: -6.11 | G116: Consolidated first (v4) – needs verification for flagged rows | H116: 30.620001 | I116: 17 | L116: UNVERIFIED – negative EPS | M116: -5.01 | N116: -2.78 | O116: 33.81 | P116: 52.49 | Q116: 29.43 | R116: MISMATCH_NEEDS_CORRECTION | S116: 33.81 | T116: 30-07-2026 09:42 IST
A117: 30 | B117: 500182 | C117: Hero MotoCorp Ltd | D117: 2015 | F117: 118.42 | G117: Consolidated first (v4) – needs verification for flagged rows | H117: 3149.2 | I117: 2252 | L117: OK | M117: 26.59 | N117: 19.02 | O117: 5297.8 | P117: 6388.5 | Q117: 4201 | R117: MISMATCH_NEEDS_CORRECTION | S117: 5297.8 | T117: 30-07-2026 09:42 IST
A118: 30 | B118: 500182 | C118: Hero MotoCorp Ltd | D118: 2016 | F118: 157.34 | G118: Consolidated first (v4) – needs verification for flagged rows | H118: 3739.8999 | I118: 2410 | L118: OK | M118: 23.77 | N118: 15.32 | O118: 5297.8 | P118: 6388.5 | Q118: 4201 | R118: MISMATCH_NEEDS_CORRECTION | S118: 5297.8 | T118: 30-07-2026 09:42 IST
A119: 30 | B119: 500182 | C119: Hero MotoCorp Ltd | D119: 2017 | F119: 179.49 | G119: Consolidated first (v4) – needs verification for flagged rows | H119: 4200 | I119: 2966 | L119: OK | M119: 23.4 | N119: 16.52 | O119: 5297.8 | P119: 6388.5 | Q119: 4201 | R119: MISMATCH_NEEDS_CORRECTION | S119: 5297.8 | T119: 30-07-2026 09:42 IST
A120: 30 | B120: 500182 | C120: Hero MotoCorp Ltd | D120: 2018 | F120: 186.29 | G120: Consolidated first (v4) – needs verification for flagged rows | H120: 3862 | I120: 2648.7 | L120: OK | M120: 20.73 | N120: 14.22 | O120: 5297.8 | P120: 6388.5 | Q120: 4201 | R120: MISMATCH_NEEDS_CORRECTION | S120: 5297.8 | T120: 30-07-2026 09:42 IST
A121: 30 | B121: 500182 | C121: Hero MotoCorp Ltd | D121: 2019 | F121: 172.44 | G121: Consolidated first (v4) – needs verification for flagged rows | H121: 3123 | I121: 2228.25 | L121: OK | M121: 18.11 | N121: 12.92 | O121: 5297.8 | P121: 6388.5 | Q121: 4201 | R121: MISMATCH_NEEDS_CORRECTION | S121: 5297.8 | T121: 30-07-2026 09:42 IST
A122: 30 | B122: 500182 | C122: Hero MotoCorp Ltd | D122: 2020 | F122: 182.14 | G122: Consolidated first (v4) – needs verification for flagged rows | H122: 3393.8501 | I122: 1475 | L122: OK | M122: 18.63 | N122: 8.1 | O122: 5297.8 | P122: 6388.5 | Q122: 4201 | R122: MISMATCH_NEEDS_CORRECTION | S122: 5297.8 | T122: 30-07-2026 09:42 IST
A123: 30 | B123: 500182 | C123: Hero MotoCorp Ltd | D123: 2021 | F123: 146.05 | G123: Consolidated first (v4) – needs verification for flagged rows | H123: 3628.55 | I123: 2310.5 | L123: OK | M123: 24.84 | N123: 15.82 | O123: 5297.8 | P123: 6388.5 | Q123: 4201 | R123: MISMATCH_NEEDS_CORRECTION | S123: 5297.8 | T123: 30-07-2026 09:42 IST
A124: 30 | B124: 500182 | C124: Hero MotoCorp Ltd | D124: 2022 | F124: 115.95 | G124: Consolidated first (v4) – needs verification for flagged rows | H124: 2939.3501 | I124: 2148 | L124: OK | M124: 25.35 | N124: 18.53 | O124: 5297.8 | P124: 6388.5 | Q124: 4201 | R124: MISMATCH_NEEDS_CORRECTION | S124: 5297.8 | T124: 30-07-2026 09:42 IST
A125: 30 | B125: 500182 | C125: Hero MotoCorp Ltd | D125: 2023 | F125: 140.61 | G125: Consolidated first (v4) – needs verification for flagged rows | H125: 4194.8501 | I125: 2246.75 | L125: OK | M125: 29.83 | N125: 15.98 | O125: 5297.8 | P125: 6388.5 | Q125: 4201 | R125: MISMATCH_NEEDS_CORRECTION | S125: 5297.8 | T125: 30-07-2026 09:42 IST
A126: 30 | B126: 500182 | C126: Hero MotoCorp Ltd | D126: 2024 | F126: 187.31 | G126: Consolidated first (v4) – needs verification for flagged rows | H126: 6245 | I126: 3930.3 | L126: OK | M126: 33.34 | N126: 20.98 | O126: 5297.8 | P126: 6388.5 | Q126: 4201 | R126: MISMATCH_NEEDS_CORRECTION | S126: 5297.8 | T126: 30-07-2026 09:42 IST
A127: 30 | B127: 500182 | C127: Hero MotoCorp Ltd | D127: 2025 | F127: 218.91 | G127: Consolidated first (v4) – needs verification for flagged rows | H127: 6390 | I127: 3322.6001 | L127: OK | M127: 29.19 | N127: 15.18 | O127: 5297.8 | P127: 6388.5 | Q127: 4201 | R127: MISMATCH_NEEDS_CORRECTION | S127: 5297.8 | T127: 30-07-2026 09:42 IST
A128: 30 | B128: 500182 | C128: Hero MotoCorp Ltd | D128: 2026 | F128: 286.96 | G128: Consolidated first (v4) – needs verification for flagged rows | H128: 6049.9502 | I128: 4671.5498 | L128: OK | M128: 21.08 | N128: 16.28 | O128: 5297.8 | P128: 6388.5 | Q128: 4201 | R128: MISMATCH_NEEDS_CORRECTION | S128: 5297.8 | T128: 30-07-2026 09:42 IST
A129: 31 | B129: 500184 | C129: Himadri Speciality Chemical Ltd | D129: 2015 | E129: 790.59998 | F129: 2.48 | G129: Consolidated first (v4) – needs verification for flagged rows | H129: 27.9 | L129: UNVERIFIED – negative EPS | M129: 11.25 | O129: 761.8 | P129: 819.5 | Q129: 418.5 | R129: VERIFIED_OK | S129: 761.8 | T129: 30-07-2026 09:42 IST
A130: 31 | B130: 500184 | C130: Himadri Speciality Chemical Ltd | D130: 2016 | E130: 790.59998 | F130: 2.74 | G130: Consolidated first (v4) – needs verification for flagged rows | H130: 47.75 | I130: 12.8 | L130: UNVERIFIED – negative EPS | M130: 17.43 | N130: 4.67 | O130: 761.8 | P130: 819.5 | Q130: 418.5 | R130: VERIFIED_OK | S130: 761.8 | T130: 30-07-2026 09:42 IST
A131: 31 | B131: 500184 | C131: Himadri Speciality Chemical Ltd | D131: 2017 | E131: 790.59998 | F131: 1.98 | G131: Consolidated first (v4) – needs verification for flagged rows | H131: 178.3 | I131: 33.349998 | L131: OK | M131: 90.05 | N131: 16.84 | O131: 761.8 | P131: 819.5 | Q131: 418.5 | R131: VERIFIED_OK | S131: 761.8 | T131: 30-07-2026 09:42 IST
A132: 31 | B132: 500184 | C132: Himadri Speciality Chemical Ltd | D132: 2018 | E132: 790.59998 | F132: 5.91 | G132: Consolidated first (v4) – needs verification for flagged rows | H132: 195.8 | I132: 103.55 | L132: OK | M132: 33.13 | N132: 17.52 | O132: 761.8 | P132: 819.5 | Q132: 418.5 | R132: VERIFIED_OK | S132: 761.8 | T132: 30-07-2026 09:42 IST
A133: 31 | B133: 500184 | C133: Himadri Speciality Chemical Ltd | D133: 2019 | E133: 790.59998 | F133: 7.75 | G133: Consolidated first (v4) – needs verification for flagged rows | H133: 137.89999 | I133: 54.099998 | L133: OK | M133: 17.79 | N133: 6.98 | O133: 761.8 | P133: 819.5 | Q133: 418.5 | R133: VERIFIED_OK | S133: 761.8 | T133: 30-07-2026 09:42 IST
A134: 31 | B134: 500184 | C134: Himadri Speciality Chemical Ltd | D134: 2020 | E134: 790.59998 | F134: 4.91 | G134: Consolidated first (v4) – needs verification for flagged rows | H134: 73.900002 | I134: 27.299999 | L134: OK | M134: 15.05 | N134: 5.56 | O134: 761.8 | P134: 819.5 | Q134: 418.5 | R134: VERIFIED_OK | S134: 761.8 | T134: 30-07-2026 09:42 IST
A135: 31 | B135: 500184 | C135: Himadri Speciality Chemical Ltd | D135: 2021 | E135: 790.59998 | F135: 1.13 | G135: Consolidated first (v4) – needs verification for flagged rows | H135: 62.400002 | I135: 38.900002 | L135: OK | M135: 55.22 | N135: 34.42 | O135: 761.8 | P135: 819.5 | Q135: 418.5 | R135: VERIFIED_OK | S135: 761.8 | T135: 30-07-2026 09:42 IST
A136: 31 | B136: 500184 | C136: Himadri Speciality Chemical Ltd | D136: 2022 | E136: 790.59998 | F136: 0.98 | G136: Consolidated first (v4) – needs verification for flagged rows | H136: 108.85 | I136: 44.5 | L136: OK | M136: 111.07 | N136: 45.41 | O136: 761.8 | P136: 819.5 | Q136: 418.5 | R136: VERIFIED_OK | S136: 761.8 | T136: 30-07-2026 09:42 IST
A137: 31 | B137: 500184 | C137: Himadri Speciality Chemical Ltd | D137: 2023 | E137: 790.59998 | F137: 4.99 | G137: Consolidated first (v4) – needs verification for flagged rows | H137: 313.89999 | I137: 80.199997 | L137: OK | M137: 62.91 | N137: 16.07 | O137: 761.8 | P137: 819.5 | Q137: 418.5 | R137: VERIFIED_OK | S137: 761.8 | T137: 30-07-2026 09:42 IST
A138: 31 | B138: 500184 | C138: Himadri Speciality Chemical Ltd | D138: 2024 | E138: 790.59998 | F138: 8.34 | G138: Consolidated first (v4) – needs verification for flagged rows | H138: 688.5 | I138: 272.79999 | L138: OK | M138: 82.55 | N138: 32.71 | O138: 761.8 | P138: 819.5 | Q138: 418.5 | R138: VERIFIED_OK | S138: 761.8 | T138: 30-07-2026 09:42 IST
A139: 31 | B139: 500184 | C139: Himadri Speciality Chemical Ltd | D139: 2025 | E139: 790.59998 | F139: 11.25 | G139: Consolidated first (v4) – needs verification for flagged rows | H139: 606.54999 | I139: 351.39999 | L139: OK | M139: 53.92 | N139: 31.24 | O139: 761.8 | P139: 819.5 | Q139: 418.5 | R139: VERIFIED_OK | S139: 761.8 | T139: 30-07-2026 09:42 IST
A140: 31 | B140: 500184 | C140: Himadri Speciality Chemical Ltd | D140: 2026 | E140: 790.59998 | F140: 14.89 | G140: Consolidated first (v4) – needs verification for flagged rows | H140: 819.5 | I140: 421.20001 | L140: OK | M140: 55.04 | N140: 28.29 | O140: 761.8 | P140: 819.5 | Q140: 418.5 | R140: VERIFIED_OK | S140: 761.8 | T140: 30-07-2026 09:42 IST
A141: 36 | B141: 500199 | C141: IG Petrochemicals Ltd | D141: 2015 | E141: 425.45001 | G141: Consolidated first (v4) – needs verification for flagged rows | H141: 174.39999 | I141: 40 | L141: INCOMPLETE | O141: =IFERROR(VLOOKUP(B141,BSE_500_LIVE!A:E,3,FALSE),"") | P141: =IFERROR(VLOOKUP(B141,BSE_500_LIVE!A:E,4,FALSE),"") | Q141: =IFERROR(VLOOKUP(B141,BSE_500_LIVE!A:E,5,FALSE),"") | R141: =IF(OR(E141="",O141=""),"PENDING_FETCH",IF(ABS(E141-O141)/E141>0.005,"MISMATCH_NEEDS_CORRECTION","VERIFIED_OK")) | S141: =IF(O141<>"",O141,E141) | T141: =IFERROR(VLOOKUP(B141,BSE_500_LIVE!A:F,6,FALSE),"")
A142: 36 | B142: 500199 | C142: IG Petrochemicals Ltd | D142: 2016 | E142: 425.45001 | F142: 19.55 | G142: Consolidated first (v4) – needs verification for flagged rows | H142: 347 | I142: 72 | L142: OK | M142: 17.75 | N142: 3.68 | O142: =IFERROR(VLOOKUP(B142,BSE_500_LIVE!A:E,3,FALSE),"") | P142: =IFERROR(VLOOKUP(B142,BSE_500_LIVE!A:E,4,FALSE),"") | Q142: =IFERROR(VLOOKUP(B142,BSE_500_LIVE!A:E,5,FALSE),"") | R142: =IF(OR(E142="",O142=""),"PENDING_FETCH",IF(ABS(E142-O142)/E142>0.005,"MISMATCH_NEEDS_CORRECTION","VERIFIED_OK")) | S142: =IF(O142<>"",O142,E142) | T142: =IFERROR(VLOOKUP(B142,BSE_500_LIVE!A:F,6,FALSE),"")
A143: 36 | B143: 500199 | C143: IG Petrochemicals Ltd | D143: 2017 | E143: 425.45001 | F143: 32.98 | G143: Consolidated first (v4) – needs verification for flagged rows | H143: 796.09998 | I143: 224 | L143: OK | M143: 24.14 | N143: 6.79 | O143: =IFERROR(VLOOKUP(B143,BSE_500_LIVE!A:E,3,FALSE),"") | P143: =IFERROR(VLOOKUP(B143,BSE_500_LIVE!A:E,4,FALSE),"") | Q143: =IFERROR(VLOOKUP(B143,BSE_500_LIVE!A:E,5,FALSE),"") | R143: =IF(OR(E143="",O143=""),"PENDING_FETCH",IF(ABS(E143-O143)/E143>0.005,"MISMATCH_NEEDS_CORRECTION","VERIFIED_OK")) | S143: =IF(O143<>"",O143,E143) | T143: =IFERROR(VLOOKUP(B143,BSE_500_LIVE!A:F,6,FALSE),"")
A144: 36 | B144: 500199 | C144: IG Petrochemicals Ltd | D144: 2018 | E144: 425.45001 | F144: 47.42 | G144: Consolidated first (v4) – needs verification for flagged rows | H144: 840 | I144: 340 | L144: OK | M144: 17.71 | N144: 7.17 | O144: =IFERROR(VLOOKUP(B144,BSE_500_LIVE!A:E,3,FALSE),"") | P144: =IFERROR(VLOOKUP(B144,BSE_500_LIVE!A:E,4,FALSE),"") | Q144: =IFERROR(VLOOKUP(B144,BSE_500_LIVE!A:E,5,FALSE),"") | R144: =IF(OR(E144="",O144=""),"PENDING_FETCH",IF(ABS(E144-O144)/E144>0.005,"MISMATCH_NEEDS_CORRECTION","VERIFIED_OK")) | S144: =IF(O144<>"",O144,E144) | T144: =IFERROR(VLOOKUP(B144,BSE_500_LIVE!A:F,6,FALSE),"")
A145: 36 | B145: 500199 | C145: IG Petrochemicals Ltd | D145: 2019 | E145: 425.45001 | F145: 37.94 | G145: Consolidated first (v4) – needs verification for flagged rows | H145: 429.10001 | I145: 125 | L145: OK | M145: 11.31 | N145: 3.29 | O145: =IFERROR(VLOOKUP(B145,BSE_500_LIVE!A:E,3,FALSE),"") | P145: =IFERROR(VLOOKUP(B145,BSE_500_LIVE!A:E,4,FALSE),"") | Q145: =IFERROR(VLOOKUP(B145,BSE_500_LIVE!A:E,5,FALSE),"") | R145: =IF(OR(E145="",O145=""),"PENDING_FETCH",IF(ABS(E145-O145)/E145>0.005,"MISMATCH_NEEDS_CORRECTION","VERIFIED_OK")) | S145: =IF(O145<>"",O145,E145) | T145: =IFERROR(VLOOKUP(B145,BSE_500_LIVE!A:F,6,FALSE),"")
A146: 36 | B146: 500199 | C146: IG Petrochemicals Ltd | D146: 2020 | E146: 425.45001 | F146: 6.78 | G146: Consolidated first (v4) – needs verification for flagged rows | H146: 501 | I146: 81.25 | L146: OK | M146: 73.89 | N146: 11.98 | O146: =IFERROR(VLOOKUP(B146,BSE_500_LIVE!A:E,3,FALSE),"") | P146: =IFERROR(VLOOKUP(B146,BSE_500_LIVE!A:E,4,FALSE),"") | Q146: =IFERROR(VLOOKUP(B146,BSE_500_LIVE!A:E,5,FALSE),"") | R146: =IF(OR(E146="",O146=""),"PENDING_FETCH",IF(ABS(E146-O146)/E146>0.005,"MISMATCH_NEEDS_CORRECTION","VERIFIED_OK")) | S146: =IF(O146<>"",O146,E146) | T146: =IFERROR(VLOOKUP(B146,BSE_500_LIVE!A:F,6,FALSE),"")
A147: 36 | B147: 500199 | C147: IG Petrochemicals Ltd | D147: 2021 | E147: 425.45001 | F147: 61.08 | G147: Consolidated first (v4) – needs verification for flagged rows | H147: 1017.9 | I147: 363.10001 | L147: OK | M147: 16.67 | N147: 5.94 | O147: =IFERROR(VLOOKUP(B147,BSE_500_LIVE!A:E,3,FALSE),"") | P147: =IFERROR(VLOOKUP(B147,BSE_500_LIVE!A:E,4,FALSE),"") | Q147: =IFERROR(VLOOKUP(B147,BSE_500_LIVE!A:E,5,FALSE),"") | R147: =IF(OR(E147="",O147=""),"PENDING_FETCH",IF(ABS(E147-O147)/E147>0.005,"MISMATCH_NEEDS_CORRECTION","VERIFIED_OK")) | S147: =IF(O147<>"",O147,E147) | T147: =IFERROR(VLOOKUP(B147,BSE_500_LIVE!A:F,6,FALSE),"")
A148: 36 | B148: 500199 | C148: IG Petrochemicals Ltd | D148: 2022 | E148: 425.45001 | F148: 85.89 | G148: Consolidated first (v4) – needs verification for flagged rows | H148: 827.5 | I148: 490.95001 | L148: OK | M148: 9.63 | N148: 5.72 | O148: =IFERROR(VLOOKUP(B148,BSE_500_LIVE!A:E,3,FALSE),"") | P148: =IFERROR(VLOOKUP(B148,BSE_500_LIVE!A:E,4,FALSE),"") | Q148: =IFERROR(VLOOKUP(B148,BSE_500_LIVE!A:E,5,FALSE),"") | R148: =IF(OR(E148="",O148=""),"PENDING_FETCH",IF(ABS(E148-O148)/E148>0.005,"MISMATCH_NEEDS_CORRECTION","VERIFIED_OK")) | S148: =IF(O148<>"",O148,E148) | T148: =IFERROR(VLOOKUP(B148,BSE_500_LIVE!A:F,6,FALSE),"")
A149: 36 | B149: 500199 | C149: IG Petrochemicals Ltd | D149: 2023 | E149: 425.45001 | F149: 64.95 | G149: Consolidated first (v4) – needs verification for flagged rows | H149: 588.54999 | I149: 393 | L149: OK | M149: 9.06 | N149: 6.05 | O149: =IFERROR(VLOOKUP(B149,BSE_500_LIVE!A:E,3,FALSE),"") | P149: =IFERROR(VLOOKUP(B149,BSE_500_LIVE!A:E,4,FALSE),"") | Q149: =IFERROR(VLOOKUP(B149,BSE_500_LIVE!A:E,5,FALSE),"") | R149: =IF(OR(E149="",O149=""),"PENDING_FETCH",IF(ABS(E149-O149)/E149>0.005,"MISMATCH_NEEDS_CORRECTION","VERIFIED_OK")) | S149: =IF(O149<>"",O149,E149) | T149: =IFERROR(VLOOKUP(B149,BSE_500_LIVE!A:F,6,FALSE),"")
A150: 36 | B150: 500199 | C150: IG Petrochemicals Ltd | D150: 2024 | E150: 425.45001 | F150: 12.83 | G150: Consolidated first (v4) – needs verification for flagged rows | H150: 725.59998 | I150: 406.64999 | L150: OK | M150: 56.55 | N150: 31.7 | O150: =IFERROR(VLOOKUP(B150,BSE_500_LIVE!A:E,3,FALSE),"") | P150: =IFERROR(VLOOKUP(B150,BSE_500_LIVE!A:E,4,FALSE),"") | Q150: =IFERROR(VLOOKUP(B150,BSE_500_LIVE!A:E,5,FALSE),"") | R150: =IF(OR(E150="",O150=""),"PENDING_FETCH",IF(ABS(E150-O150)/E150>0.005,"MISMATCH_NEEDS_CORRECTION","VERIFIED_OK")) | S150: =IF(O150<>"",O150,E150) | T150: =IFERROR(VLOOKUP(B150,BSE_500_LIVE!A:F,6,FALSE),"")
A151: 36 | B151: 500199 | C151: IG Petrochemicals Ltd | D151: 2025 | E151: 425.45001 | F151: 35.3 | G151: Consolidated first (v4) – needs verification for flagged rows | H151: 587 | I151: 360.89999 | L151: OK | M151: 16.63 | N151: 10.22 | O151: =IFERROR(VLOOKUP(B151,BSE_500_LIVE!A:E,3,FALSE),"") | P151: =IFERROR(VLOOKUP(B151,BSE_500_LIVE!A:E,4,FALSE),"") | Q151: =IFERROR(VLOOKUP(B151,BSE_500_LIVE!A:E,5,FALSE),"") | R151: =IF(OR(E151="",O151=""),"PENDING_FETCH",IF(ABS(E151-O151)/E151>0.005,"MISMATCH_NEEDS_CORRECTION","VERIFIED_OK")) | S151: =IF(O151<>"",O151,E151) | T151: =IFERROR(VLOOKUP(B151,BSE_500_LIVE!A:F,6,FALSE),"")
A152: 36 | B152: 500199 | C152: IG Petrochemicals Ltd | D152: 2026 | E152: 425.45001 | F152: 0.72 | G152: Consolidated first (v4) – needs verification for flagged rows | H152: 480 | I152: 317.79999 | L152: OK | M152: 666.67 | N152: 441.39 | O152: =IFERROR(VLOOKUP(B152,BSE_500_LIVE!A:E,3,FALSE),"") | P152: =IFERROR(VLOOKUP(B152,BSE_500_LIVE!A:E,4,FALSE),"") | Q152: =IFERROR(VLOOKUP(B152,BSE_500_LIVE!A:E,5,FALSE),"") | R152: =IF(OR(E152="",O152=""),"PENDING_FETCH",IF(ABS(E152-O152)/E152>0.005,"MISMATCH_NEEDS_CORRECTION","VERIFIED_OK")) | S152: =IF(O152<>"",O152,E152) | T152: =IFERROR(VLOOKUP(B152,BSE_500_LIVE!A:F,6,FALSE),"")
A153: 37 | B153: 500202 | C153: India Glycols Ltd | D153: 2015 | E153: 6.71 | F153: 9.75 | G153: Consolidated first (v4) – needs verification for flagged rows | H153: 12.87 | I153: 5.52 | L153: UNVERIFIED – negative EPS | M153: 1.32 | N153: 0.57 | O153: 8.85 | P153: 16.7 | Q153: 8.23 | R153: MISMATCH_NEEDS_CORRECTION | S153: 8.85 | T153: 30-07-2026 09:42 IST
A154: 37 | B154: 500202 | C154: India Glycols Ltd | D154: 2016 | E154: 6.71 | F154: 8.03 | G154: Consolidated first (v4) – needs verification for flagged rows | H154: 15.12 | I154: 7.2199998 | L154: UNVERIFIED – tiny EPS <0.5 | M154: 1.88 | N154: 0.9 | O154: 8.85 | P154: 16.7 | Q154: 8.23 | R154: MISMATCH_NEEDS_CORRECTION | S154: 8.85 | T154: 30-07-2026 09:42 IST
A155: 37 | B155: 500202 | C155: India Glycols Ltd | D155: 2017 | E155: 6.71 | F155: 9.18 | G155: Consolidated first (v4) – needs verification for flagged rows | H155: 8.3999996 | I155: 3.45 | L155: UNVERIFIED – negative EPS | M155: 0.92 | N155: 0.38 | O155: 8.85 | P155: 16.7 | Q155: 8.23 | R155: MISMATCH_NEEDS_CORRECTION | S155: 8.85 | T155: 30-07-2026 09:42 IST
A156: 37 | B156: 500202 | C156: India Glycols Ltd | D156: 2018 | E156: 6.71 | F156: 10.34 | G156: Consolidated first (v4) – needs verification for flagged rows | H156: 8.6599998 | I156: 4.8800001 | L156: UNVERIFIED – tiny EPS <0.5 | M156: 0.84 | N156: 0.47 | O156: 8.85 | P156: 16.7 | Q156: 8.23 | R156: MISMATCH_NEEDS_CORRECTION | S156: 8.85 | T156: 30-07-2026 09:42 IST
A157: 37 | B157: 500202 | C157: India Glycols Ltd | D157: 2019 | E157: 6.71 | F157: 11.83 | G157: Consolidated first (v4) – needs verification for flagged rows | H157: 8.8299999 | I157: 7.5999999 | L157: UNVERIFIED – negative EPS | M157: 0.75 | N157: 0.64 | O157: 8.85 | P157: 16.7 | Q157: 8.23 | R157: MISMATCH_NEEDS_CORRECTION | S157: 8.85 | T157: 30-07-2026 09:42 IST
A158: 37 | B158: 500202 | C158: India Glycols Ltd | D158: 2020 | E158: 6.71 | F158: 0.89 | G158: Consolidated first (v4) – needs verification for flagged rows | H158: 9.4099998 | I158: 3.28 | L158: OK | M158: 10.57 | N158: 3.69 | O158: 8.85 | P158: 16.7 | Q158: 8.23 | R158: MISMATCH_NEEDS_CORRECTION | S158: 8.85 | T158: 30-07-2026 09:42 IST
A159: 37 | B159: 500202 | C159: India Glycols Ltd | D159: 2021 | E159: 6.71 | F159: 10.08 | G159: Consolidated first (v4) – needs verification for flagged rows | H159: 13.35 | I159: 6.4499998 | L159: UNVERIFIED – negative EPS | M159: 1.32 | N159: 0.64 | O159: 8.85 | P159: 16.7 | Q159: 8.23 | R159: MISMATCH_NEEDS_CORRECTION | S159: 8.85 | T159: 30-07-2026 09:42 IST
A160: 37 | B160: 500202 | C160: India Glycols Ltd | D160: 2022 | E160: 6.71 | F160: 12.96 | G160: Consolidated first (v4) – needs verification for flagged rows | H160: 13.29 | I160: 5.0500002 | L160: UNVERIFIED – negative EPS | M160: 1.03 | N160: 0.39 | O160: 8.85 | P160: 16.7 | Q160: 8.23 | R160: MISMATCH_NEEDS_CORRECTION | S160: 8.85 | T160: 30-07-2026 09:42 IST
A161: 37 | B161: 500202 | C161: India Glycols Ltd | D161: 2023 | E161: 6.71 | F161: 8.26 | G161: Consolidated first (v4) – needs verification for flagged rows | H161: 14.3 | I161: 5.21 | L161: UNVERIFIED – negative EPS | M161: 1.73 | N161: 0.63 | O161: 8.85 | P161: 16.7 | Q161: 8.23 | R161: MISMATCH_NEEDS_CORRECTION | S161: 8.85 | T161: 30-07-2026 09:42 IST
...

Sheet LARGE CAP CORRECTIONS
A1: BSE Code | B1: Company | C1: Year | D1: Old EPS in file | E1: Corrected EPS | F1: Old PE | G1: New PE | H1: Source | I1: Status
A2: 500112 | B2: State Bank of India | C2: 2017 | D2: 0.3 | E2: 13.15 | F2: 1172 | G2: 26.8 | H2: Annual Report FY17 net profit 10,484cr / 797cr shares =13.15 – scribd table【3435303340785564242†L20-L23】 | I2: VERIFIED
A3: 500825 | B3: Britannia Industries | C3: 2017 | D3: -0.48 | E3: 36.8 | F3: -275 | G3: 95 | H3: Moneycontrol research Y/E March 2017 EPS 36.8【5364693404258100898†L13-L16】 | I3: VERIFIED
A4: 500520 | B4: Mahindra & Mahindra | C4: 2020 | D4: 1.02 | E4: 11.2 | F4: 749 | G4: 67 | H4: ICICI Direct FY20 EPS 11.2【5535724775168940871†L9-L12】 | I4: VERIFIED

Sheet VERIFICATION_LOG
A1: Timestamp IST | B1: BSE Code | C1: Company | D1: Calendar Year | E1: Field | F1: Excel Old CMP | G1: BSE Official CMP | H1: Difference % | I1: Action | J1: BSE Proof URL | K1: EPS Note
A2: =NOW() | B2: Example 500325 | C2: Reliance | D2: 2026 | E2: CMP | F2: 1500 | G2: 1520 | H2: =ABS(F2-G2)/F2*100 | I2: AUTO-CORRECTED | J2: https://www.bseindia.com/stock-share-price/reliance/500325/ | K2: EPS historical needs annual report

Sheet HOW_TO_USE_FINAL
A1: FINAL MERGED MASTER - HOW TO USE - Auto Update 10PM IST
A3: This file is your FINAL ready file - 2479 rows (2015-2026) + LIVE BSE columns
A4: Columns E = your old CMP TODAY All Years (kept as is)
A5: Columns O-T = new LIVE official columns that auto-fill from BSE_500_LIVE sheet via VLOOKUP
A7: STEPS TO MAKE IT LIVE:
A8: 1. Go to BSE_500_LIVE sheet - select A1:G222 - press Ctrl+T - name table as BSECodes
A9: 2. Data > Get Data > Blank Query > Advanced Editor > Paste M Code from previous file
A10: 3. Query will populate columns C,D,E in BSE_500_LIVE from BSE API
A11: 4. As soon as BSE_500_LIVE updates, ALL 2479 rows in PE Band DETAIL v8 auto-update via VLOOKUP formulas
A12: 5. For 10PM auto: Alt+F11 > paste VBA, save as .xlsm, schedule Task Scheduler to open at 9:59 PM
A14: WHAT GETS AUTO-CORRECTED:
A15: - Final_CMP_AutoCorrected = If BSE live exists, uses BSE official, else keeps your old
... A18: - EPS: Historical EPS (2015-2025) kept as is - BSE API only gives current TTM EPS, so only flagged
